[
  {
    "value": 1,
    "label": "bulbasaur"
  },
  {
    "value": 2,
    "label": "ivysaur"
  },
  {
    "value": 3,
    "label": "venusaur"
  },
  {
    "value": 4,
    "label": "charmander"
  },
  {
    "value": 5,
    "label": "charmeleon"
  },
  {
    "value": 6,
    "label": "charizard"
  },
  {
    "value": 7,
    "label": "squirtle"
  },
  {
    "value": 8,
    "label": "wartortle"
  },
  {
    "value": 9,
    "label": "blastoise"
  },
  {
    "value": 10,
    "label": "caterpie"
  },
  {
    "value": 11,
    "label": "metapod"
  },
  {
    "value": 12,
    "label": "butterfree"
  },
  {
    "value": 13,
    "label": "weedle"
  },
  {
    "value": 14,
    "label": "kakuna"
  },
  {
    "value": 15,
    "label": "beedrill"
  },
  {
    "value": 16,
    "label": "pidgey"
  },
  {
    "value": 17,
    "label": "pidgeotto"
  },
  {
    "value": 18,
    "label": "pidgeot"
  },
  {
    "value": 19,
    "label": "rattata"
  },
  {
    "value": 20,
    "label": "raticate"
  },
  {
    "value": 21,
    "label": "spearow"
  },
  {
    "value": 22,
    "label": "fearow"
  },
  {
    "value": 23,
    "label": "ekans"
  },
  {
    "value": 24,
    "label": "arbok"
  },
  {
    "value": 25,
    "label": "pikachu"
  },
  {
    "value": 26,
    "label": "raichu"
  },
  {
    "value": 27,
    "label": "sandshrew"
  },
  {
    "value": 28,
    "label": "sandslash"
  },
  {
    "value": 29,
    "label": "nidoran-f"
  },
  {
    "value": 30,
    "label": "nidorina"
  },
  {
    "value": 31,
    "label": "nidoqueen"
  },
  {
    "value": 32,
    "label": "nidoran-m"
  },
  {
    "value": 33,
    "label": "nidorino"
  },
  {
    "value": 34,
    "label": "nidoking"
  },
  {
    "value": 35,
    "label": "clefairy"
  },
  {
    "value": 36,
    "label": "clefable"
  },
  {
    "value": 37,
    "label": "vulpix"
  },
  {
    "value": 38,
    "label": "ninetales"
  },
  {
    "value": 39,
    "label": "jigglypuff"
  },
  {
    "value": 40,
    "label": "wigglytuff"
  },
  {
    "value": 41,
    "label": "zubat"
  },
  {
    "value": 42,
    "label": "golbat"
  },
  {
    "value": 43,
    "label": "oddish"
  },
  {
    "value": 44,
    "label": "gloom"
  },
  {
    "value": 45,
    "label": "vileplume"
  },
  {
    "value": 46,
    "label": "paras"
  },
  {
    "value": 47,
    "label": "parasect"
  },
  {
    "value": 48,
    "label": "venonat"
  },
  {
    "value": 49,
    "label": "venomoth"
  },
  {
    "value": 50,
    "label": "diglett"
  },
  {
    "value": 51,
    "label": "dugtrio"
  },
  {
    "value": 52,
    "label": "meowth"
  },
  {
    "value": 53,
    "label": "persian"
  },
  {
    "value": 54,
    "label": "psyduck"
  },
  {
    "value": 55,
    "label": "golduck"
  },
  {
    "value": 56,
    "label": "mankey"
  },
  {
    "value": 57,
    "label": "primeape"
  },
  {
    "value": 58,
    "label": "growlithe"
  },
  {
    "value": 59,
    "label": "arcanine"
  },
  {
    "value": 60,
    "label": "poliwag"
  },
  {
    "value": 61,
    "label": "poliwhirl"
  },
  {
    "value": 62,
    "label": "poliwrath"
  },
  {
    "value": 63,
    "label": "abra"
  },
  {
    "value": 64,
    "label": "kadabra"
  },
  {
    "value": 65,
    "label": "alakazam"
  },
  {
    "value": 66,
    "label": "machop"
  },
  {
    "value": 67,
    "label": "machoke"
  },
  {
    "value": 68,
    "label": "machamp"
  },
  {
    "value": 69,
    "label": "bellsprout"
  },
  {
    "value": 70,
    "label": "weepinbell"
  },
  {
    "value": 71,
    "label": "victreebel"
  },
  {
    "value": 72,
    "label": "tentacool"
  },
  {
    "value": 73,
    "label": "tentacruel"
  },
  {
    "value": 74,
    "label": "geodude"
  },
  {
    "value": 75,
    "label": "graveler"
  },
  {
    "value": 76,
    "label": "golem"
  },
  {
    "value": 77,
    "label": "ponyta"
  },
  {
    "value": 78,
    "label": "rapidash"
  },
  {
    "value": 79,
    "label": "slowpoke"
  },
  {
    "value": 80,
    "label": "slowbro"
  },
  {
    "value": 81,
    "label": "magnemite"
  },
  {
    "value": 82,
    "label": "magneton"
  },
  {
    "value": 83,
    "label": "farfetchd"
  },
  {
    "value": 84,
    "label": "doduo"
  },
  {
    "value": 85,
    "label": "dodrio"
  },
  {
    "value": 86,
    "label": "seel"
  },
  {
    "value": 87,
    "label": "dewgong"
  },
  {
    "value": 88,
    "label": "grimer"
  },
  {
    "value": 89,
    "label": "muk"
  },
  {
    "value": 90,
    "label": "shellder"
  },
  {
    "value": 91,
    "label": "cloyster"
  },
  {
    "value": 92,
    "label": "gastly"
  },
  {
    "value": 93,
    "label": "haunter"
  },
  {
    "value": 94,
    "label": "gengar"
  },
  {
    "value": 95,
    "label": "onix"
  },
  {
    "value": 96,
    "label": "drowzee"
  },
  {
    "value": 97,
    "label": "hypno"
  },
  {
    "value": 98,
    "label": "krabby"
  },
  {
    "value": 99,
    "label": "kingler"
  },
  {
    "value": 100,
    "label": "voltorb"
  },
  {
    "value": 101,
    "label": "electrode"
  },
  {
    "value": 102,
    "label": "exeggcute"
  },
  {
    "value": 103,
    "label": "exeggutor"
  },
  {
    "value": 104,
    "label": "cubone"
  },
  {
    "value": 105,
    "label": "marowak"
  },
  {
    "value": 106,
    "label": "hitmonlee"
  },
  {
    "value": 107,
    "label": "hitmonchan"
  },
  {
    "value": 108,
    "label": "lickitung"
  },
  {
    "value": 109,
    "label": "koffing"
  },
  {
    "value": 110,
    "label": "weezing"
  },
  {
    "value": 111,
    "label": "rhyhorn"
  },
  {
    "value": 112,
    "label": "rhydon"
  },
  {
    "value": 113,
    "label": "chansey"
  },
  {
    "value": 114,
    "label": "tangela"
  },
  {
    "value": 115,
    "label": "kangaskhan"
  },
  {
    "value": 116,
    "label": "horsea"
  },
  {
    "value": 117,
    "label": "seadra"
  },
  {
    "value": 118,
    "label": "goldeen"
  },
  {
    "value": 119,
    "label": "seaking"
  },
  {
    "value": 120,
    "label": "staryu"
  },
  {
    "value": 121,
    "label": "starmie"
  },
  {
    "value": 122,
    "label": "mr-mime"
  },
  {
    "value": 123,
    "label": "scyther"
  },
  {
    "value": 124,
    "label": "jynx"
  },
  {
    "value": 125,
    "label": "electabuzz"
  },
  {
    "value": 126,
    "label": "magmar"
  },
  {
    "value": 127,
    "label": "pinsir"
  },
  {
    "value": 128,
    "label": "tauros"
  },
  {
    "value": 129,
    "label": "magikarp"
  },
  {
    "value": 130,
    "label": "gyarados"
  },
  {
    "value": 131,
    "label": "lapras"
  },
  {
    "value": 132,
    "label": "ditto"
  },
  {
    "value": 133,
    "label": "eevee"
  },
  {
    "value": 134,
    "label": "vaporeon"
  },
  {
    "value": 135,
    "label": "jolteon"
  },
  {
    "value": 136,
    "label": "flareon"
  },
  {
    "value": 137,
    "label": "porygon"
  },
  {
    "value": 138,
    "label": "omanyte"
  },
  {
    "value": 139,
    "label": "omastar"
  },
  {
    "value": 140,
    "label": "kabuto"
  },
  {
    "value": 141,
    "label": "kabutops"
  },
  {
    "value": 142,
    "label": "aerodactyl"
  },
  {
    "value": 143,
    "label": "snorlax"
  },
  {
    "value": 144,
    "label": "articuno"
  },
  {
    "value": 145,
    "label": "zapdos"
  },
  {
    "value": 146,
    "label": "moltres"
  },
  {
    "value": 147,
    "label": "dratini"
  },
  {
    "value": 148,
    "label": "dragonair"
  },
  {
    "value": 149,
    "label": "dragonite"
  },
  {
    "value": 150,
    "label": "mewtwo"
  },
  {
    "value": 151,
    "label": "mew"
  },
  {
    "value": 152,
    "label": "chikorita"
  },
  {
    "value": 153,
    "label": "bayleef"
  },
  {
    "value": 154,
    "label": "meganium"
  },
  {
    "value": 155,
    "label": "cyndaquil"
  },
  {
    "value": 156,
    "label": "quilava"
  },
  {
    "value": 157,
    "label": "typhlosion"
  },
  {
    "value": 158,
    "label": "totodile"
  },
  {
    "value": 159,
    "label": "croconaw"
  },
  {
    "value": 160,
    "label": "feraligatr"
  },
  {
    "value": 161,
    "label": "sentret"
  },
  {
    "value": 162,
    "label": "furret"
  },
  {
    "value": 163,
    "label": "hoothoot"
  },
  {
    "value": 164,
    "label": "noctowl"
  },
  {
    "value": 165,
    "label": "ledyba"
  },
  {
    "value": 166,
    "label": "ledian"
  },
  {
    "value": 167,
    "label": "spinarak"
  },
  {
    "value": 168,
    "label": "ariados"
  },
  {
    "value": 169,
    "label": "crobat"
  },
  {
    "value": 170,
    "label": "chinchou"
  },
  {
    "value": 171,
    "label": "lanturn"
  },
  {
    "value": 172,
    "label": "pichu"
  },
  {
    "value": 173,
    "label": "cleffa"
  },
  {
    "value": 174,
    "label": "igglybuff"
  },
  {
    "value": 175,
    "label": "togepi"
  },
  {
    "value": 176,
    "label": "togetic"
  },
  {
    "value": 177,
    "label": "natu"
  },
  {
    "value": 178,
    "label": "xatu"
  },
  {
    "value": 179,
    "label": "mareep"
  },
  {
    "value": 180,
    "label": "flaaffy"
  },
  {
    "value": 181,
    "label": "ampharos"
  },
  {
    "value": 182,
    "label": "bellossom"
  },
  {
    "value": 183,
    "label": "marill"
  },
  {
    "value": 184,
    "label": "azumarill"
  },
  {
    "value": 185,
    "label": "sudowoodo"
  },
  {
    "value": 186,
    "label": "politoed"
  },
  {
    "value": 187,
    "label": "hoppip"
  },
  {
    "value": 188,
    "label": "skiploom"
  },
  {
    "value": 189,
    "label": "jumpluff"
  },
  {
    "value": 190,
    "label": "aipom"
  },
  {
    "value": 191,
    "label": "sunkern"
  },
  {
    "value": 192,
    "label": "sunflora"
  },
  {
    "value": 193,
    "label": "yanma"
  },
  {
    "value": 194,
    "label": "wooper"
  },
  {
    "value": 195,
    "label": "quagsire"
  },
  {
    "value": 196,
    "label": "espeon"
  },
  {
    "value": 197,
    "label": "umbreon"
  },
  {
    "value": 198,
    "label": "murkrow"
  },
  {
    "value": 199,
    "label": "slowking"
  },
  {
    "value": 200,
    "label": "misdreavus"
  },
  {
    "value": 201,
    "label": "unown"
  },
  {
    "value": 202,
    "label": "wobbuffet"
  },
  {
    "value": 203,
    "label": "girafarig"
  },
  {
    "value": 204,
    "label": "pineco"
  },
  {
    "value": 205,
    "label": "forretress"
  },
  {
    "value": 206,
    "label": "dunsparce"
  },
  {
    "value": 207,
    "label": "gligar"
  },
  {
    "value": 208,
    "label": "steelix"
  },
  {
    "value": 209,
    "label": "snubbull"
  },
  {
    "value": 210,
    "label": "granbull"
  },
  {
    "value": 211,
    "label": "qwilfish"
  },
  {
    "value": 212,
    "label": "scizor"
  },
  {
    "value": 213,
    "label": "shuckle"
  },
  {
    "value": 214,
    "label": "heracross"
  },
  {
    "value": 215,
    "label": "sneasel"
  },
  {
    "value": 216,
    "label": "teddiursa"
  },
  {
    "value": 217,
    "label": "ursaring"
  },
  {
    "value": 218,
    "label": "slugma"
  },
  {
    "value": 219,
    "label": "magcargo"
  },
  {
    "value": 220,
    "label": "swinub"
  },
  {
    "value": 221,
    "label": "piloswine"
  },
  {
    "value": 222,
    "label": "corsola"
  },
  {
    "value": 223,
    "label": "remoraid"
  },
  {
    "value": 224,
    "label": "octillery"
  },
  {
    "value": 225,
    "label": "delibird"
  },
  {
    "value": 226,
    "label": "mantine"
  },
  {
    "value": 227,
    "label": "skarmory"
  },
  {
    "value": 228,
    "label": "houndour"
  },
  {
    "value": 229,
    "label": "houndoom"
  },
  {
    "value": 230,
    "label": "kingdra"
  },
  {
    "value": 231,
    "label": "phanpy"
  },
  {
    "value": 232,
    "label": "donphan"
  },
  {
    "value": 233,
    "label": "porygon2"
  },
  {
    "value": 234,
    "label": "stantler"
  },
  {
    "value": 235,
    "label": "smeargle"
  },
  {
    "value": 236,
    "label": "tyrogue"
  },
  {
    "value": 237,
    "label": "hitmontop"
  },
  {
    "value": 238,
    "label": "smoochum"
  },
  {
    "value": 239,
    "label": "elekid"
  },
  {
    "value": 240,
    "label": "magby"
  },
  {
    "value": 241,
    "label": "miltank"
  },
  {
    "value": 242,
    "label": "blissey"
  },
  {
    "value": 243,
    "label": "raikou"
  },
  {
    "value": 244,
    "label": "entei"
  },
  {
    "value": 245,
    "label": "suicune"
  },
  {
    "value": 246,
    "label": "larvitar"
  },
  {
    "value": 247,
    "label": "pupitar"
  },
  {
    "value": 248,
    "label": "tyranitar"
  },
  {
    "value": 249,
    "label": "lugia"
  },
  {
    "value": 250,
    "label": "ho-oh"
  },
  {
    "value": 251,
    "label": "celebi"
  },
  {
    "value": 252,
    "label": "treecko"
  },
  {
    "value": 253,
    "label": "grovyle"
  },
  {
    "value": 254,
    "label": "sceptile"
  },
  {
    "value": 255,
    "label": "torchic"
  },
  {
    "value": 256,
    "label": "combusken"
  },
  {
    "value": 257,
    "label": "blaziken"
  },
  {
    "value": 258,
    "label": "mudkip"
  },
  {
    "value": 259,
    "label": "marshtomp"
  },
  {
    "value": 260,
    "label": "swampert"
  },
  {
    "value": 261,
    "label": "poochyena"
  },
  {
    "value": 262,
    "label": "mightyena"
  },
  {
    "value": 263,
    "label": "zigzagoon"
  },
  {
    "value": 264,
    "label": "linoone"
  },
  {
    "value": 265,
    "label": "wurmple"
  },
  {
    "value": 266,
    "label": "silcoon"
  },
  {
    "value": 267,
    "label": "beautifly"
  },
  {
    "value": 268,
    "label": "cascoon"
  },
  {
    "value": 269,
    "label": "dustox"
  },
  {
    "value": 270,
    "label": "lotad"
  },
  {
    "value": 271,
    "label": "lombre"
  },
  {
    "value": 272,
    "label": "ludicolo"
  },
  {
    "value": 273,
    "label": "seedot"
  },
  {
    "value": 274,
    "label": "nuzleaf"
  },
  {
    "value": 275,
    "label": "shiftry"
  },
  {
    "value": 276,
    "label": "taillow"
  },
  {
    "value": 277,
    "label": "swellow"
  },
  {
    "value": 278,
    "label": "wingull"
  },
  {
    "value": 279,
    "label": "pelipper"
  },
  {
    "value": 280,
    "label": "ralts"
  },
  {
    "value": 281,
    "label": "kirlia"
  },
  {
    "value": 282,
    "label": "gardevoir"
  },
  {
    "value": 283,
    "label": "surskit"
  },
  {
    "value": 284,
    "label": "masquerain"
  },
  {
    "value": 285,
    "label": "shroomish"
  },
  {
    "value": 286,
    "label": "breloom"
  },
  {
    "value": 287,
    "label": "slakoth"
  },
  {
    "value": 288,
    "label": "vigoroth"
  },
  {
    "value": 289,
    "label": "slaking"
  },
  {
    "value": 290,
    "label": "nincada"
  },
  {
    "value": 291,
    "label": "ninjask"
  },
  {
    "value": 292,
    "label": "shedinja"
  },
  {
    "value": 293,
    "label": "whismur"
  },
  {
    "value": 294,
    "label": "loudred"
  },
  {
    "value": 295,
    "label": "exploud"
  },
  {
    "value": 296,
    "label": "makuhita"
  },
  {
    "value": 297,
    "label": "hariyama"
  },
  {
    "value": 298,
    "label": "azurill"
  },
  {
    "value": 299,
    "label": "nosepass"
  },
  {
    "value": 300,
    "label": "skitty"
  },
  {
    "value": 301,
    "label": "delcatty"
  },
  {
    "value": 302,
    "label": "sableye"
  },
  {
    "value": 303,
    "label": "mawile"
  },
  {
    "value": 304,
    "label": "aron"
  },
  {
    "value": 305,
    "label": "lairon"
  },
  {
    "value": 306,
    "label": "aggron"
  },
  {
    "value": 307,
    "label": "meditite"
  },
  {
    "value": 308,
    "label": "medicham"
  },
  {
    "value": 309,
    "label": "electrike"
  },
  {
    "value": 310,
    "label": "manectric"
  },
  {
    "value": 311,
    "label": "plusle"
  },
  {
    "value": 312,
    "label": "minun"
  },
  {
    "value": 313,
    "label": "volbeat"
  },
  {
    "value": 314,
    "label": "illumise"
  },
  {
    "value": 315,
    "label": "roselia"
  },
  {
    "value": 316,
    "label": "gulpin"
  },
  {
    "value": 317,
    "label": "swalot"
  },
  {
    "value": 318,
    "label": "carvanha"
  },
  {
    "value": 319,
    "label": "sharpedo"
  },
  {
    "value": 320,
    "label": "wailmer"
  },
  {
    "value": 321,
    "label": "wailord"
  },
  {
    "value": 322,
    "label": "numel"
  },
  {
    "value": 323,
    "label": "camerupt"
  },
  {
    "value": 324,
    "label": "torkoal"
  },
  {
    "value": 325,
    "label": "spoink"
  },
  {
    "value": 326,
    "label": "grumpig"
  },
  {
    "value": 327,
    "label": "spinda"
  },
  {
    "value": 328,
    "label": "trapinch"
  },
  {
    "value": 329,
    "label": "vibrava"
  },
  {
    "value": 330,
    "label": "flygon"
  },
  {
    "value": 331,
    "label": "cacnea"
  },
  {
    "value": 332,
    "label": "cacturne"
  },
  {
    "value": 333,
    "label": "swablu"
  },
  {
    "value": 334,
    "label": "altaria"
  },
  {
    "value": 335,
    "label": "zangoose"
  },
  {
    "value": 336,
    "label": "seviper"
  },
  {
    "value": 337,
    "label": "lunatone"
  },
  {
    "value": 338,
    "label": "solrock"
  },
  {
    "value": 339,
    "label": "barboach"
  },
  {
    "value": 340,
    "label": "whiscash"
  },
  {
    "value": 341,
    "label": "corphish"
  },
  {
    "value": 342,
    "label": "crawdaunt"
  },
  {
    "value": 343,
    "label": "baltoy"
  },
  {
    "value": 344,
    "label": "claydol"
  },
  {
    "value": 345,
    "label": "lileep"
  },
  {
    "value": 346,
    "label": "cradily"
  },
  {
    "value": 347,
    "label": "anorith"
  },
  {
    "value": 348,
    "label": "armaldo"
  },
  {
    "value": 349,
    "label": "feebas"
  },
  {
    "value": 350,
    "label": "milotic"
  },
  {
    "value": 351,
    "label": "castform"
  },
  {
    "value": 352,
    "label": "kecleon"
  },
  {
    "value": 353,
    "label": "shuppet"
  },
  {
    "value": 354,
    "label": "banette"
  },
  {
    "value": 355,
    "label": "duskull"
  },
  {
    "value": 356,
    "label": "dusclops"
  },
  {
    "value": 357,
    "label": "tropius"
  },
  {
    "value": 358,
    "label": "chimecho"
  },
  {
    "value": 359,
    "label": "absol"
  },
  {
    "value": 360,
    "label": "wynaut"
  },
  {
    "value": 361,
    "label": "snorunt"
  },
  {
    "value": 362,
    "label": "glalie"
  },
  {
    "value": 363,
    "label": "spheal"
  },
  {
    "value": 364,
    "label": "sealeo"
  },
  {
    "value": 365,
    "label": "walrein"
  },
  {
    "value": 366,
    "label": "clamperl"
  },
  {
    "value": 367,
    "label": "huntail"
  },
  {
    "value": 368,
    "label": "gorebyss"
  },
  {
    "value": 369,
    "label": "relicanth"
  },
  {
    "value": 370,
    "label": "luvdisc"
  },
  {
    "value": 371,
    "label": "bagon"
  },
  {
    "value": 372,
    "label": "shelgon"
  },
  {
    "value": 373,
    "label": "salamence"
  },
  {
    "value": 374,
    "label": "beldum"
  },
  {
    "value": 375,
    "label": "metang"
  },
  {
    "value": 376,
    "label": "metagross"
  },
  {
    "value": 377,
    "label": "regirock"
  },
  {
    "value": 378,
    "label": "regice"
  },
  {
    "value": 379,
    "label": "registeel"
  },
  {
    "value": 380,
    "label": "latias"
  },
  {
    "value": 381,
    "label": "latios"
  },
  {
    "value": 382,
    "label": "kyogre"
  },
  {
    "value": 383,
    "label": "groudon"
  },
  {
    "value": 384,
    "label": "rayquaza"
  },
  {
    "value": 385,
    "label": "jirachi"
  },
  {
    "value": 386,
    "label": "deoxys-normal"
  },
  {
    "value": 387,
    "label": "turtwig"
  },
  {
    "value": 388,
    "label": "grotle"
  },
  {
    "value": 389,
    "label": "torterra"
  },
  {
    "value": 390,
    "label": "chimchar"
  },
  {
    "value": 391,
    "label": "monferno"
  },
  {
    "value": 392,
    "label": "infernape"
  },
  {
    "value": 393,
    "label": "piplup"
  },
  {
    "value": 394,
    "label": "prinplup"
  },
  {
    "value": 395,
    "label": "empoleon"
  },
  {
    "value": 396,
    "label": "starly"
  },
  {
    "value": 397,
    "label": "staravia"
  },
  {
    "value": 398,
    "label": "staraptor"
  },
  {
    "value": 399,
    "label": "bidoof"
  },
  {
    "value": 400,
    "label": "bibarel"
  },
  {
    "value": 401,
    "label": "kricketot"
  },
  {
    "value": 402,
    "label": "kricketune"
  },
  {
    "value": 403,
    "label": "shinx"
  },
  {
    "value": 404,
    "label": "luxio"
  },
  {
    "value": 405,
    "label": "luxray"
  },
  {
    "value": 406,
    "label": "budew"
  },
  {
    "value": 407,
    "label": "roserade"
  },
  {
    "value": 408,
    "label": "cranidos"
  },
  {
    "value": 409,
    "label": "rampardos"
  },
  {
    "value": 410,
    "label": "shieldon"
  },
  {
    "value": 411,
    "label": "bastiodon"
  },
  {
    "value": 412,
    "label": "burmy"
  },
  {
    "value": 413,
    "label": "wormadam-plant"
  },
  {
    "value": 414,
    "label": "mothim"
  },
  {
    "value": 415,
    "label": "combee"
  },
  {
    "value": 416,
    "label": "vespiquen"
  },
  {
    "value": 417,
    "label": "pachirisu"
  },
  {
    "value": 418,
    "label": "buizel"
  },
  {
    "value": 419,
    "label": "floatzel"
  },
  {
    "value": 420,
    "label": "cherubi"
  },
  {
    "value": 421,
    "label": "cherrim"
  },
  {
    "value": 422,
    "label": "shellos"
  },
  {
    "value": 423,
    "label": "gastrodon"
  },
  {
    "value": 424,
    "label": "ambipom"
  },
  {
    "value": 425,
    "label": "drifloon"
  },
  {
    "value": 426,
    "label": "drifblim"
  },
  {
    "value": 427,
    "label": "buneary"
  },
  {
    "value": 428,
    "label": "lopunny"
  },
  {
    "value": 429,
    "label": "mismagius"
  },
  {
    "value": 430,
    "label": "honchkrow"
  },
  {
    "value": 431,
    "label": "glameow"
  },
  {
    "value": 432,
    "label": "purugly"
  },
  {
    "value": 433,
    "label": "chingling"
  },
  {
    "value": 434,
    "label": "stunky"
  },
  {
    "value": 435,
    "label": "skuntank"
  },
  {
    "value": 436,
    "label": "bronzor"
  },
  {
    "value": 437,
    "label": "bronzong"
  },
  {
    "value": 438,
    "label": "bonsly"
  },
  {
    "value": 439,
    "label": "mime-jr"
  },
  {
    "value": 440,
    "label": "happiny"
  },
  {
    "value": 441,
    "label": "chatot"
  },
  {
    "value": 442,
    "label": "spiritomb"
  },
  {
    "value": 443,
    "label": "gible"
  },
  {
    "value": 444,
    "label": "gabite"
  },
  {
    "value": 445,
    "label": "garchomp"
  },
  {
    "value": 446,
    "label": "munchlax"
  },
  {
    "value": 447,
    "label": "riolu"
  },
  {
    "value": 448,
    "label": "lucario"
  },
  {
    "value": 449,
    "label": "hippopotas"
  },
  {
    "value": 450,
    "label": "hippowdon"
  },
  {
    "value": 451,
    "label": "skorupi"
  },
  {
    "value": 452,
    "label": "drapion"
  },
  {
    "value": 453,
    "label": "croagunk"
  },
  {
    "value": 454,
    "label": "toxicroak"
  },
  {
    "value": 455,
    "label": "carnivine"
  },
  {
    "value": 456,
    "label": "finneon"
  },
  {
    "value": 457,
    "label": "lumineon"
  },
  {
    "value": 458,
    "label": "mantyke"
  },
  {
    "value": 459,
    "label": "snover"
  },
  {
    "value": 460,
    "label": "abomasnow"
  },
  {
    "value": 461,
    "label": "weavile"
  },
  {
    "value": 462,
    "label": "magnezone"
  },
  {
    "value": 463,
    "label": "lickilicky"
  },
  {
    "value": 464,
    "label": "rhyperior"
  },
  {
    "value": 465,
    "label": "tangrowth"
  },
  {
    "value": 466,
    "label": "electivire"
  },
  {
    "value": 467,
    "label": "magmortar"
  },
  {
    "value": 468,
    "label": "togekiss"
  },
  {
    "value": 469,
    "label": "yanmega"
  },
  {
    "value": 470,
    "label": "leafeon"
  },
  {
    "value": 471,
    "label": "glaceon"
  },
  {
    "value": 472,
    "label": "gliscor"
  },
  {
    "value": 473,
    "label": "mamoswine"
  },
  {
    "value": 474,
    "label": "porygon-z"
  },
  {
    "value": 475,
    "label": "gallade"
  },
  {
    "value": 476,
    "label": "probopass"
  },
  {
    "value": 477,
    "label": "dusknoir"
  },
  {
    "value": 478,
    "label": "froslass"
  },
  {
    "value": 479,
    "label": "rotom"
  },
  {
    "value": 480,
    "label": "uxie"
  },
  {
    "value": 481,
    "label": "mesprit"
  },
  {
    "value": 482,
    "label": "azelf"
  },
  {
    "value": 483,
    "label": "dialga"
  },
  {
    "value": 484,
    "label": "palkia"
  },
  {
    "value": 485,
    "label": "heatran"
  },
  {
    "value": 486,
    "label": "regigigas"
  },
  {
    "value": 487,
    "label": "giratina-altered"
  },
  {
    "value": 488,
    "label": "cresselia"
  },
  {
    "value": 489,
    "label": "phione"
  },
  {
    "value": 490,
    "label": "manaphy"
  },
  {
    "value": 491,
    "label": "darkrai"
  },
  {
    "value": 492,
    "label": "shaymin-land"
  },
  {
    "value": 493,
    "label": "arceus"
  },
  {
    "value": 494,
    "label": "victini"
  },
  {
    "value": 495,
    "label": "snivy"
  },
  {
    "value": 496,
    "label": "servine"
  },
  {
    "value": 497,
    "label": "serperior"
  },
  {
    "value": 498,
    "label": "tepig"
  },
  {
    "value": 499,
    "label": "pignite"
  },
  {
    "value": 500,
    "label": "emboar"
  },
  {
    "value": 501,
    "label": "oshawott"
  },
  {
    "value": 502,
    "label": "dewott"
  },
  {
    "value": 503,
    "label": "samurott"
  },
  {
    "value": 504,
    "label": "patrat"
  },
  {
    "value": 505,
    "label": "watchog"
  },
  {
    "value": 506,
    "label": "lillipup"
  },
  {
    "value": 507,
    "label": "herdier"
  },
  {
    "value": 508,
    "label": "stoutland"
  },
  {
    "value": 509,
    "label": "purrloin"
  },
  {
    "value": 510,
    "label": "liepard"
  },
  {
    "value": 511,
    "label": "pansage"
  },
  {
    "value": 512,
    "label": "simisage"
  },
  {
    "value": 513,
    "label": "pansear"
  },
  {
    "value": 514,
    "label": "simisear"
  },
  {
    "value": 515,
    "label": "panpour"
  },
  {
    "value": 516,
    "label": "simipour"
  },
  {
    "value": 517,
    "label": "munna"
  },
  {
    "value": 518,
    "label": "musharna"
  },
  {
    "value": 519,
    "label": "pidove"
  },
  {
    "value": 520,
    "label": "tranquill"
  },
  {
    "value": 521,
    "label": "unfezant"
  },
  {
    "value": 522,
    "label": "blitzle"
  },
  {
    "value": 523,
    "label": "zebstrika"
  },
  {
    "value": 524,
    "label": "roggenrola"
  },
  {
    "value": 525,
    "label": "boldore"
  },
  {
    "value": 526,
    "label": "gigalith"
  },
  {
    "value": 527,
    "label": "woobat"
  },
  {
    "value": 528,
    "label": "swoobat"
  },
  {
    "value": 529,
    "label": "drilbur"
  },
  {
    "value": 530,
    "label": "excadrill"
  },
  {
    "value": 531,
    "label": "audino"
  },
  {
    "value": 532,
    "label": "timburr"
  },
  {
    "value": 533,
    "label": "gurdurr"
  },
  {
    "value": 534,
    "label": "conkeldurr"
  },
  {
    "value": 535,
    "label": "tympole"
  },
  {
    "value": 536,
    "label": "palpitoad"
  },
  {
    "value": 537,
    "label": "seismitoad"
  },
  {
    "value": 538,
    "label": "throh"
  },
  {
    "value": 539,
    "label": "sawk"
  },
  {
    "value": 540,
    "label": "sewaddle"
  },
  {
    "value": 541,
    "label": "swadloon"
  },
  {
    "value": 542,
    "label": "leavanny"
  },
  {
    "value": 543,
    "label": "venipede"
  },
  {
    "value": 544,
    "label": "whirlipede"
  },
  {
    "value": 545,
    "label": "scolipede"
  },
  {
    "value": 546,
    "label": "cottonee"
  },
  {
    "value": 547,
    "label": "whimsicott"
  },
  {
    "value": 548,
    "label": "petilil"
  },
  {
    "value": 549,
    "label": "lilligant"
  },
  {
    "value": 550,
    "label": "basculin-red-striped"
  },
  {
    "value": 551,
    "label": "sandile"
  },
  {
    "value": 552,
    "label": "krokorok"
  },
  {
    "value": 553,
    "label": "krookodile"
  },
  {
    "value": 554,
    "label": "darumaka"
  },
  {
    "value": 555,
    "label": "darmanitan-standard"
  },
  {
    "value": 556,
    "label": "maractus"
  },
  {
    "value": 557,
    "label": "dwebble"
  },
  {
    "value": 558,
    "label": "crustle"
  },
  {
    "value": 559,
    "label": "scraggy"
  },
  {
    "value": 560,
    "label": "scrafty"
  },
  {
    "value": 561,
    "label": "sigilyph"
  },
  {
    "value": 562,
    "label": "yamask"
  },
  {
    "value": 563,
    "label": "cofagrigus"
  },
  {
    "value": 564,
    "label": "tirtouga"
  },
  {
    "value": 565,
    "label": "carracosta"
  },
  {
    "value": 566,
    "label": "archen"
  },
  {
    "value": 567,
    "label": "archeops"
  },
  {
    "value": 568,
    "label": "trubbish"
  },
  {
    "value": 569,
    "label": "garbodor"
  },
  {
    "value": 570,
    "label": "zorua"
  },
  {
    "value": 571,
    "label": "zoroark"
  },
  {
    "value": 572,
    "label": "minccino"
  },
  {
    "value": 573,
    "label": "cinccino"
  },
  {
    "value": 574,
    "label": "gothita"
  },
  {
    "value": 575,
    "label": "gothorita"
  },
  {
    "value": 576,
    "label": "gothitelle"
  },
  {
    "value": 577,
    "label": "solosis"
  },
  {
    "value": 578,
    "label": "duosion"
  },
  {
    "value": 579,
    "label": "reuniclus"
  },
  {
    "value": 580,
    "label": "ducklett"
  },
  {
    "value": 581,
    "label": "swanna"
  },
  {
    "value": 582,
    "label": "vanillite"
  },
  {
    "value": 583,
    "label": "vanillish"
  },
  {
    "value": 584,
    "label": "vanilluxe"
  },
  {
    "value": 585,
    "label": "deerling"
  },
  {
    "value": 586,
    "label": "sawsbuck"
  },
  {
    "value": 587,
    "label": "emolga"
  },
  {
    "value": 588,
    "label": "karrablast"
  },
  {
    "value": 589,
    "label": "escavalier"
  },
  {
    "value": 590,
    "label": "foongus"
  },
  {
    "value": 591,
    "label": "amoonguss"
  },
  {
    "value": 592,
    "label": "frillish"
  },
  {
    "value": 593,
    "label": "jellicent"
  },
  {
    "value": 594,
    "label": "alomomola"
  },
  {
    "value": 595,
    "label": "joltik"
  },
  {
    "value": 596,
    "label": "galvantula"
  },
  {
    "value": 597,
    "label": "ferroseed"
  },
  {
    "value": 598,
    "label": "ferrothorn"
  },
  {
    "value": 599,
    "label": "klink"
  },
  {
    "value": 600,
    "label": "klang"
  },
  {
    "value": 601,
    "label": "klinklang"
  },
  {
    "value": 602,
    "label": "tynamo"
  },
  {
    "value": 603,
    "label": "eelektrik"
  },
  {
    "value": 604,
    "label": "eelektross"
  },
  {
    "value": 605,
    "label": "elgyem"
  },
  {
    "value": 606,
    "label": "beheeyem"
  },
  {
    "value": 607,
    "label": "litwick"
  },
  {
    "value": 608,
    "label": "lampent"
  },
  {
    "value": 609,
    "label": "chandelure"
  },
  {
    "value": 610,
    "label": "axew"
  },
  {
    "value": 611,
    "label": "fraxure"
  },
  {
    "value": 612,
    "label": "haxorus"
  },
  {
    "value": 613,
    "label": "cubchoo"
  },
  {
    "value": 614,
    "label": "beartic"
  },
  {
    "value": 615,
    "label": "cryogonal"
  },
  {
    "value": 616,
    "label": "shelmet"
  },
  {
    "value": 617,
    "label": "accelgor"
  },
  {
    "value": 618,
    "label": "stunfisk"
  },
  {
    "value": 619,
    "label": "mienfoo"
  },
  {
    "value": 620,
    "label": "mienshao"
  },
  {
    "value": 621,
    "label": "druddigon"
  },
  {
    "value": 622,
    "label": "golett"
  },
  {
    "value": 623,
    "label": "golurk"
  },
  {
    "value": 624,
    "label": "pawniard"
  },
  {
    "value": 625,
    "label": "bisharp"
  },
  {
    "value": 626,
    "label": "bouffalant"
  },
  {
    "value": 627,
    "label": "rufflet"
  },
  {
    "value": 628,
    "label": "braviary"
  },
  {
    "value": 629,
    "label": "vullaby"
  },
  {
    "value": 630,
    "label": "mandibuzz"
  },
  {
    "value": 631,
    "label": "heatmor"
  },
  {
    "value": 632,
    "label": "durant"
  },
  {
    "value": 633,
    "label": "deino"
  },
  {
    "value": 634,
    "label": "zweilous"
  },
  {
    "value": 635,
    "label": "hydreigon"
  },
  {
    "value": 636,
    "label": "larvesta"
  },
  {
    "value": 637,
    "label": "volcarona"
  },
  {
    "value": 638,
    "label": "cobalion"
  },
  {
    "value": 639,
    "label": "terrakion"
  },
  {
    "value": 640,
    "label": "virizion"
  },
  {
    "value": 641,
    "label": "tornadus-incarnate"
  },
  {
    "value": 642,
    "label": "thundurus-incarnate"
  },
  {
    "value": 643,
    "label": "reshiram"
  },
  {
    "value": 644,
    "label": "zekrom"
  },
  {
    "value": 645,
    "label": "landorus-incarnate"
  },
  {
    "value": 646,
    "label": "kyurem"
  },
  {
    "value": 647,
    "label": "keldeo-ordinary"
  },
  {
    "value": 648,
    "label": "meloetta-aria"
  },
  {
    "value": 649,
    "label": "genesect"
  },
  {
    "value": 650,
    "label": "chespin"
  },
  {
    "value": 651,
    "label": "quilladin"
  },
  {
    "value": 652,
    "label": "chesnaught"
  },
  {
    "value": 653,
    "label": "fennekin"
  },
  {
    "value": 654,
    "label": "braixen"
  },
  {
    "value": 655,
    "label": "delphox"
  },
  {
    "value": 656,
    "label": "froakie"
  },
  {
    "value": 657,
    "label": "frogadier"
  },
  {
    "value": 658,
    "label": "greninja"
  },
  {
    "value": 659,
    "label": "bunnelby"
  },
  {
    "value": 660,
    "label": "diggersby"
  },
  {
    "value": 661,
    "label": "fletchling"
  },
  {
    "value": 662,
    "label": "fletchinder"
  },
  {
    "value": 663,
    "label": "talonflame"
  },
  {
    "value": 664,
    "label": "scatterbug"
  },
  {
    "value": 665,
    "label": "spewpa"
  },
  {
    "value": 666,
    "label": "vivillon"
  },
  {
    "value": 667,
    "label": "litleo"
  },
  {
    "value": 668,
    "label": "pyroar"
  },
  {
    "value": 669,
    "label": "flabebe"
  },
  {
    "value": 670,
    "label": "floette"
  },
  {
    "value": 671,
    "label": "florges"
  },
  {
    "value": 672,
    "label": "skiddo"
  },
  {
    "value": 673,
    "label": "gogoat"
  },
  {
    "value": 674,
    "label": "pancham"
  },
  {
    "value": 675,
    "label": "pangoro"
  },
  {
    "value": 676,
    "label": "furfrou"
  },
  {
    "value": 677,
    "label": "espurr"
  },
  {
    "value": 678,
    "label": "meowstic-male"
  },
  {
    "value": 679,
    "label": "honedge"
  },
  {
    "value": 680,
    "label": "doublade"
  },
  {
    "value": 681,
    "label": "aegislash-shield"
  },
  {
    "value": 682,
    "label": "spritzee"
  },
  {
    "value": 683,
    "label": "aromatisse"
  },
  {
    "value": 684,
    "label": "swirlix"
  },
  {
    "value": 685,
    "label": "slurpuff"
  },
  {
    "value": 686,
    "label": "inkay"
  },
  {
    "value": 687,
    "label": "malamar"
  },
  {
    "value": 688,
    "label": "binacle"
  },
  {
    "value": 689,
    "label": "barbaracle"
  },
  {
    "value": 690,
    "label": "skrelp"
  },
  {
    "value": 691,
    "label": "dragalge"
  },
  {
    "value": 692,
    "label": "clauncher"
  },
  {
    "value": 693,
    "label": "clawitzer"
  },
  {
    "value": 694,
    "label": "helioptile"
  },
  {
    "value": 695,
    "label": "heliolisk"
  },
  {
    "value": 696,
    "label": "tyrunt"
  },
  {
    "value": 697,
    "label": "tyrantrum"
  },
  {
    "value": 698,
    "label": "amaura"
  },
  {
    "value": 699,
    "label": "aurorus"
  },
  {
    "value": 700,
    "label": "sylveon"
  },
  {
    "value": 701,
    "label": "hawlucha"
  },
  {
    "value": 702,
    "label": "dedenne"
  },
  {
    "value": 703,
    "label": "carbink"
  },
  {
    "value": 704,
    "label": "goomy"
  },
  {
    "value": 705,
    "label": "sliggoo"
  },
  {
    "value": 706,
    "label": "goodra"
  },
  {
    "value": 707,
    "label": "klefki"
  },
  {
    "value": 708,
    "label": "phantump"
  },
  {
    "value": 709,
    "label": "trevenant"
  },
  {
    "value": 710,
    "label": "pumpkaboo-average"
  },
  {
    "value": 711,
    "label": "gourgeist-average"
  },
  {
    "value": 712,
    "label": "bergmite"
  },
  {
    "value": 713,
    "label": "avalugg"
  },
  {
    "value": 714,
    "label": "noibat"
  },
  {
    "value": 715,
    "label": "noivern"
  },
  {
    "value": 716,
    "label": "xerneas"
  },
  {
    "value": 717,
    "label": "yveltal"
  },
  {
    "value": 718,
    "label": "zygarde"
  },
  {
    "value": 719,
    "label": "diancie"
  },
  {
    "value": 720,
    "label": "hoopa"
  },
  {
    "value": 721,
    "label": "volcanion"
  },
  {
    "value": 722,
    "label": "rowlet"
  },
  {
    "value": 723,
    "label": "dartrix"
  },
  {
    "value": 724,
    "label": "decidueye"
  },
  {
    "value": 725,
    "label": "litten"
  },
  {
    "value": 726,
    "label": "torracat"
  },
  {
    "value": 727,
    "label": "incineroar"
  },
  {
    "value": 728,
    "label": "popplio"
  },
  {
    "value": 729,
    "label": "brionne"
  },
  {
    "value": 730,
    "label": "primarina"
  },
  {
    "value": 731,
    "label": "pikipek"
  },
  {
    "value": 732,
    "label": "trumbeak"
  },
  {
    "value": 733,
    "label": "toucannon"
  },
  {
    "value": 734,
    "label": "yungoos"
  },
  {
    "value": 735,
    "label": "gumshoos"
  },
  {
    "value": 736,
    "label": "grubbin"
  },
  {
    "value": 737,
    "label": "charjabug"
  },
  {
    "value": 738,
    "label": "vikavolt"
  },
  {
    "value": 739,
    "label": "crabrawler"
  },
  {
    "value": 740,
    "label": "crabominable"
  },
  {
    "value": 741,
    "label": "oricorio-baile"
  },
  {
    "value": 742,
    "label": "cutiefly"
  },
  {
    "value": 743,
    "label": "ribombee"
  },
  {
    "value": 744,
    "label": "rockruff"
  },
  {
    "value": 745,
    "label": "lycanroc-midday"
  },
  {
    "value": 746,
    "label": "wishiwashi-solo"
  },
  {
    "value": 747,
    "label": "mareanie"
  },
  {
    "value": 748,
    "label": "toxapex"
  },
  {
    "value": 749,
    "label": "mudbray"
  },
  {
    "value": 750,
    "label": "mudsdale"
  },
  {
    "value": 751,
    "label": "dewpider"
  },
  {
    "value": 752,
    "label": "araquanid"
  },
  {
    "value": 753,
    "label": "fomantis"
  },
  {
    "value": 754,
    "label": "lurantis"
  },
  {
    "value": 755,
    "label": "morelull"
  },
  {
    "value": 756,
    "label": "shiinotic"
  },
  {
    "value": 757,
    "label": "salandit"
  },
  {
    "value": 758,
    "label": "salazzle"
  },
  {
    "value": 759,
    "label": "stufful"
  },
  {
    "value": 760,
    "label": "bewear"
  },
  {
    "value": 761,
    "label": "bounsweet"
  },
  {
    "value": 762,
    "label": "steenee"
  },
  {
    "value": 763,
    "label": "tsareena"
  },
  {
    "value": 764,
    "label": "comfey"
  },
  {
    "value": 765,
    "label": "oranguru"
  },
  {
    "value": 766,
    "label": "passimian"
  },
  {
    "value": 767,
    "label": "wimpod"
  },
  {
    "value": 768,
    "label": "golisopod"
  },
  {
    "value": 769,
    "label": "sandygast"
  },
  {
    "value": 770,
    "label": "palossand"
  },
  {
    "value": 771,
    "label": "pyukumuku"
  },
  {
    "value": 772,
    "label": "type-null"
  },
  {
    "value": 773,
    "label": "silvally"
  },
  {
    "value": 774,
    "label": "minior-red-meteor"
  },
  {
    "value": 775,
    "label": "komala"
  },
  {
    "value": 776,
    "label": "turtonator"
  },
  {
    "value": 777,
    "label": "togedemaru"
  },
  {
    "value": 778,
    "label": "mimikyu-disguised"
  },
  {
    "value": 779,
    "label": "bruxish"
  },
  {
    "value": 780,
    "label": "drampa"
  },
  {
    "value": 781,
    "label": "dhelmise"
  },
  {
    "value": 782,
    "label": "jangmo-o"
  },
  {
    "value": 783,
    "label": "hakamo-o"
  },
  {
    "value": 784,
    "label": "kommo-o"
  },
  {
    "value": 785,
    "label": "tapu-koko"
  },
  {
    "value": 786,
    "label": "tapu-lele"
  },
  {
    "value": 787,
    "label": "tapu-bulu"
  },
  {
    "value": 788,
    "label": "tapu-fini"
  },
  {
    "value": 789,
    "label": "cosmog"
  },
  {
    "value": 790,
    "label": "cosmoem"
  },
  {
    "value": 791,
    "label": "solgaleo"
  },
  {
    "value": 792,
    "label": "lunala"
  },
  {
    "value": 793,
    "label": "nihilego"
  },
  {
    "value": 794,
    "label": "buzzwole"
  },
  {
    "value": 795,
    "label": "pheromosa"
  },
  {
    "value": 796,
    "label": "xurkitree"
  },
  {
    "value": 797,
    "label": "celesteela"
  },
  {
    "value": 798,
    "label": "kartana"
  },
  {
    "value": 799,
    "label": "guzzlord"
  },
  {
    "value": 800,
    "label": "necrozma"
  },
  {
    "value": 801,
    "label": "magearna"
  },
  {
    "value": 802,
    "label": "marshadow"
  },
  {
    "value": 803,
    "label": "poipole"
  },
  {
    "value": 804,
    "label": "naganadel"
  },
  {
    "value": 805,
    "label": "stakataka"
  },
  {
    "value": 806,
    "label": "blacephalon"
  },
  {
    "value": 807,
    "label": "zeraora"
  }
]